{
  "schema": "p47_model_based_search_config_v1",
  "seeds": [
    "AAAAAAA",
    "BBBBBBB",
    "CCCCCCC",
    "DDDDDDD"
  ],
  "world_model": {
    "checkpoint": "",
    "eval_ref": ""
  },
  "candidate_actions": {
    "source": "heuristic_candidates",
    "top_k": 5,
    "seed": "AAAAAAA",
    "target_phase": "SELECTING_HAND",
    "search_max_branch": 96,
    "search_max_depth": 2,
    "search_time_budget_ms": 20.0
  },
  "planner": {
    "horizon": 2,
    "gamma": 0.95,
    "reward_weight": 1.0,
    "score_weight": 0.5,
    "value_weight": 0.2,
    "terminal_bonus": 0.0,
    "uncertainty_penalty": 0.6,
    "branching_strategy": "repeat_action"
  },
  "arena_compare": {
    "backend": "sim",
    "mode": "long_episode",
    "baseline_policy": "heuristic_baseline",
    "champion_policy": "heuristic_baseline",
    "candidate_policy": "heuristic_wm_rerank_h2",
    "include_search_baseline": true,
    "episodes_per_seed": 2,
    "max_steps": 180,
    "timeout_sec": 5400,
    "enable_champion_rules": true,
    "champion_json": "docs/artifacts/p22/champion.json",
    "variants": [
      {
        "id": "heuristic_wm_rerank_h1",
        "base_policy": "heuristic_baseline",
        "candidate_source": "heuristic_candidates",
        "top_k": 5,
        "horizon": 1,
        "uncertainty_penalty": 0.6
      },
      {
        "id": "heuristic_wm_rerank_h2",
        "base_policy": "heuristic_baseline",
        "candidate_source": "heuristic_candidates",
        "top_k": 5,
        "horizon": 2,
        "uncertainty_penalty": 0.6
      },
      {
        "id": "heuristic_wm_rerank_h1_low_unc",
        "base_policy": "heuristic_baseline",
        "candidate_source": "heuristic_candidates",
        "top_k": 5,
        "horizon": 1,
        "uncertainty_penalty": 0.25
      },
      {
        "id": "search_wm_rerank_h1",
        "base_policy": "search_expert",
        "candidate_source": "search_candidates",
        "top_k": 4,
        "horizon": 1,
        "uncertainty_penalty": 0.6,
        "search_max_branch": 96,
        "search_max_depth": 2,
        "search_time_budget_ms": 20.0
      }
    ]
  },
  "triage": {
    "output_artifacts_root": "docs/artifacts/p47/triage"
  },
  "output": {
    "artifacts_root": "docs/artifacts/p47/arena_ablation"
  },
  "__yaml_source_sha256__": "173217e314e37e04835a9445a323585e119bed0a48f440d7f64d4551d5cfb83d"
}
